martin_binance/__init__.py
martin_binance/client.py
martin_binance/db_utils.py
martin_binance/executor.py
martin_binance/lib.py
martin_binance/params.py
martin_binance/strategy_base.py
martin_binance/backtest/OoTSP.py
martin_binance/backtest/VCoSEL.py
martin_binance/backtest/__init__.py
martin_binance/backtest/exchange_simulator.py
martin_binance/backtest/optimizer.py
martin_binance/service/.tmux.conf
martin_binance/service/funds_export.service
martin_binance/service/funds_rate_exporter.py
martin_binance/service/grafana.json
martin_binance/service/relaunch.py
martin_binance/service/relaunch.service
martin_binance/service/tlg-proxy.service
martin_binance/telegram_proxy/tlg_client.py
martin_binance/telegram_proxy/tlg_proxy.proto
martin_binance/telegram_proxy/tlg_proxy.py
martin_binance/templates/cli_0_BTCUSDT.py
martin_binance/templates/cli_1_BTCUSDT.py
martin_binance/templates/cli_2_TESTBTCTESTUSDT.py
martin_binance/templates/cli_3_BTCUSDT.py
martin_binance/templates/funds_rate.db
martin_binance/templates/ms_cfg.toml
martin_binance/templates/trial_params.json
martin_binance/tlg/__init__.py
martin_binance-3.0.38.dist-info/entry_points.txt
martin_binance-3.0.38.dist-info/licenses/LICENSE
martin_binance-3.0.38.dist-info/WHEEL
martin_binance-3.0.38.dist-info/METADATA
martin_binance-3.0.38.dist-info/RECORD
