Metadata-Version: 2.4
Name: martin-binance
Version: 3.0.38
Summary: Free trading system for Binance SPOT API
Author-email: Jerry Fedorenko <jerry.fedorenko@yahoo.com>
Requires-Python: >=3.12
Classifier: Programming Language :: Python :: 3
Classifier: Development Status :: 5 - Production/Stable
Classifier: License :: OSI Approved :: MIT License
Classifier: Operating System :: Unix
Classifier: Operating System :: Microsoft :: Windows
Classifier: Operating System :: MacOS
License-File: LICENSE
Requires-Dist: exchanges-wrapper==2.1.46
Requires-Dist: aiofiles==25.1.0
Requires-Dist: aiocsv==1.4.0
Requires-Dist: betterproto==2.0.0b7
Requires-Dist: colorama==0.4.6
Requires-Dist: dash==2.18.2
Requires-Dist: inquirer==3.4.0
Requires-Dist: jsonpickle==4.0.2
Requires-Dist: libtmux==0.46.2
Requires-Dist: numpy~=2.4.1
Requires-Dist: optuna==4.7.0
Requires-Dist: orjson~=3.11.6
Requires-Dist: pandas==3.0.0
Requires-Dist: plotly==6.0.0
Requires-Dist: prometheus-client==0.24.1
Requires-Dist: psutil==7.2.2
Requires-Dist: pyarrow~=23.0.0
Requires-Dist: requests==2.32.5
Requires-Dist: schedule~=1.2.2
Requires-Dist: scikit-learn==1.8.0
Requires-Dist: scipy==1.17.0
Requires-Dist: shortuuid~=1.0.13
Requires-Dist: toml~=0.10.2
Requires-Dist: tqdm==4.67.1
Requires-Dist: ujson~=5.11.0
Project-URL: Source, https://github.com/DogsTailFarmer/martin-binance
